guitarsounds/__init__.py
guitarsounds/analysis.py
guitarsounds/interface.py
guitarsounds/parameters.py
guitarsounds/utils.py
guitarsounds-1.0.0.dist-info/LICENSE.txt
guitarsounds-1.0.0.dist-info/METADATA
guitarsounds-1.0.0.dist-info/WHEEL
guitarsounds-1.0.0.dist-info/top_level.txt
guitarsounds-1.0.0.dist-info/RECORD
