Metadata-Version: 2.1
Name: guitarsounds
Version: 1.0.0
Summary: A python package to analyze and visualize harmonic sounds
Home-page: https://github.com/olivecha/guitarsounds
Author: Olivier Chabot
Author-email: olivier.chabot.2@ens.etsmtl.ca
License: MIT
Project-URL: Documentation, https://olivecha.github.io/guitarsounds/
Platform: UNKNOWN
Classifier: License :: OSI Approved :: MIT License
Classifier: Programming Language :: Python :: 3
Classifier: Programming Language :: Python :: 3.9
Requires-Python: >=3
License-File: LICENSE.txt
Requires-Dist: IPython
Requires-Dist: librosa
Requires-Dist: soundfile
Requires-Dist: matplotlib
Requires-Dist: numpy
Requires-Dist: noisereduce
Requires-Dist: scipy
Requires-Dist: tabulate
Requires-Dist: timbral-models
Requires-Dist: ipywidgets
